pure_ldp/__init__.py
pure_ldp/core/__init__.py
pure_ldp/core/_freq_oracle_client.py
pure_ldp/core/_freq_oracle_server.py
pure_ldp/core/fo_creator.py
pure_ldp/core/hh_creator.py
pure_ldp/core/prob_simplex.py
pure_ldp/frequency_oracles/__init__.py
pure_ldp/frequency_oracles/apple_cms/__init__.py
pure_ldp/frequency_oracles/apple_cms/cms_client.py
pure_ldp/frequency_oracles/apple_cms/cms_sever.py
pure_ldp/frequency_oracles/direct_encoding/__init__.py
pure_ldp/frequency_oracles/direct_encoding/de_client.py
pure_ldp/frequency_oracles/direct_encoding/de_server.py
pure_ldp/frequency_oracles/hadamard_mechanism/__init__.py
pure_ldp/frequency_oracles/hadamard_mechanism/hadamard_mechanism_client.py
pure_ldp/frequency_oracles/hadamard_mechanism/hadamard_mechanism_server.py
pure_ldp/frequency_oracles/hadamard_response/__init__.py
pure_ldp/frequency_oracles/hadamard_response/hr_client.py
pure_ldp/frequency_oracles/hadamard_response/hr_server.py
pure_ldp/frequency_oracles/hadamard_response/internal/__init__.py
pure_ldp/frequency_oracles/hadamard_response/internal/functions.py
pure_ldp/frequency_oracles/hadamard_response/internal/k2k_hadamard.py
pure_ldp/frequency_oracles/histogram_encoding/__init__.py
pure_ldp/frequency_oracles/histogram_encoding/he_client.py
pure_ldp/frequency_oracles/histogram_encoding/he_server.py
pure_ldp/frequency_oracles/local_hashing/__init__.py
pure_ldp/frequency_oracles/local_hashing/fast_lh_client.py
pure_ldp/frequency_oracles/local_hashing/fast_lh_server.py
pure_ldp/frequency_oracles/local_hashing/lh_client.py
pure_ldp/frequency_oracles/local_hashing/lh_server.py
pure_ldp/frequency_oracles/priv_count_sketch/__init__.py
pure_ldp/frequency_oracles/priv_count_sketch/pcs_client.py
pure_ldp/frequency_oracles/priv_count_sketch/pcs_server.py
pure_ldp/frequency_oracles/rappor/__init__.py
pure_ldp/frequency_oracles/rappor/rappor_client.py
pure_ldp/frequency_oracles/rappor/rappor_server.py
pure_ldp/frequency_oracles/sketch_response/__init__.py
pure_ldp-1.2.0.dist-info/METADATA
pure_ldp-1.2.0.dist-info/WHEEL
pure_ldp-1.2.0.dist-info/top_level.txt
pure_ldp-1.2.0.dist-info/RECORD
