Metadata-Version: 2.1
Name: pure-ldp
Version: 1.2.0
Summary: Simple pure LDP frequency oracle implementations
Home-page: https://github.com/Samuel-Maddock/pure-LDP
Author: Samuel Maddock
Author-email: samuel-maddock@hotmail.com
License: MIT
Requires-Dist: xxhash
Requires-Dist: numpy
Requires-Dist: scipy
Requires-Dist: bitstring
Requires-Dist: bitarray
